animatetools/__init__.py
animatetools/code.py
animatetools-0.1.dist-info/LICENSE
animatetools-0.1.dist-info/METADATA
animatetools-0.1.dist-info/WHEEL
animatetools-0.1.dist-info/top_level.txt
animatetools-0.1.dist-info/RECORD
