Metadata-Version: 2.1
Name: animatetools
Version: 0.1
Summary: Tools for creating text animations.
Home-page: https://github.com/good-coder-bad-boy/animatetools
Author: GoodCoderBadBoy
Author-email: 
License: UNKNOWN
Platform: UNKNOWN
Requires-Python: >=3.6
